pytriskel/pytriskel.cpython-38-x86_64-linux-gnu.so
pytriskel/pytriskel.pyi
pytriskel/include/fmt/args.h
pytriskel/include/fmt/base.h
pytriskel/include/fmt/chrono.h
pytriskel/include/fmt/color.h
pytriskel/include/fmt/compile.h
pytriskel/include/fmt/core.h
pytriskel/include/fmt/format-inl.h
pytriskel/include/fmt/format.h
pytriskel/include/fmt/os.h
pytriskel/include/fmt/ostream.h
pytriskel/include/fmt/printf.h
pytriskel/include/fmt/ranges.h
pytriskel/include/fmt/std.h
pytriskel/include/fmt/xchar.h
pytriskel/lib64/libfmt.a
pytriskel/lib64/libtriskel.a
pytriskel/lib64/cmake/fmt/fmt-config-version.cmake
pytriskel/lib64/cmake/fmt/fmt-config.cmake
pytriskel/lib64/cmake/fmt/fmt-targets-release.cmake
pytriskel/lib64/cmake/fmt/fmt-targets.cmake
pytriskel/lib64/pkgconfig/fmt.pc
pytriskel.libs/libXau-1c1a5928.so.6.0.0
pytriskel.libs/libbrotlicommon-24c3c480.so.1.0.9
pytriskel.libs/libbrotlidec-11aaeb4b.so.1.0.9
pytriskel.libs/libbz2-0be7c010.so.1.0.8
pytriskel.libs/libcairo-a5b243c5.so.2.11704.0
pytriskel.libs/libfontconfig-1dbc2083.so.1.12.0
pytriskel.libs/libfreetype-0048fb5d.so.6.17.4
pytriskel.libs/libgraphite2-21ca00d1.so.3.2.1
pytriskel.libs/libharfbuzz-fc843b21.so.0.20704.0
pytriskel.libs/liblzma-270e41f3.so.5.2.5
pytriskel.libs/libpixman-1-1ac9df1b.so.0.40.0
pytriskel.libs/libpng16-fdd2f83f.so.16.37.0
pytriskel.libs/libxcb-2a42d220.so.1.1.0
pytriskel.libs/libxcb-render-7676d3dd.so.0.0.0
pytriskel.libs/libxcb-shm-5be6f556.so.0.0.0
pytriskel.libs/libxml2-8afba39c.so.2.9.13
pytriskel-0.5.0.dist-info/METADATA
pytriskel-0.5.0.dist-info/WHEEL
pytriskel-0.5.0.dist-info/top_level.txt
pytriskel-0.5.0.dist-info/RECORD
