Metadata-Version: 2.4
Name: pytriskel
Version: 0.5.0
Summary: CFG visualization library
Home-page: https://github.com/triskellib/triskel
Author: Jack Royer
Author-email: jack.royer@inria.fr
License: MPL2.0
Keywords: cfg,visualization,reverse-engineering
Dynamic: author
Dynamic: author-email
Dynamic: description
Dynamic: description-content-type
Dynamic: home-page
Dynamic: keywords
Dynamic: license
Dynamic: summary
